drm_protect/__init__.py
drm_protect/module309.pyc
drm_protect/module310.pyc
drm_protect/module311.pyc
drm_protect/module312.pyc
drm_protect/module313.pyc
drm_protect-0.1.6.dist-info/licenses/LICENSE
drm_protect-0.1.6.dist-info/METADATA
drm_protect-0.1.6.dist-info/WHEEL
drm_protect-0.1.6.dist-info/top_level.txt
drm_protect-0.1.6.dist-info/RECORD
