Metadata-Version: 2.4
Name: drm-protect
Version: 0.1.6
Summary: A Python module to protect source files against modification and unauthorized redistribution.
Author-email: Edward Scissorhands <scissorhands.edward@hollywood.com>
License: MIT
Project-URL: Homepage, https://pypi.org/project/drm-protect/
Project-URL: Source, https://pypi.org/project/drm-protect/
Project-URL: Issues, https://pypi.org/project/drm-protect/
Keywords: drm,copyright,protection,security,packaging
Classifier: Programming Language :: Python :: 3
Classifier: Programming Language :: Python :: 3 :: Only
Classifier: License :: OSI Approved :: MIT License
Classifier: Operating System :: OS Independent
Requires-Python: >=3.9
License-File: LICENSE
Requires-Dist: pycryptodome
Dynamic: license-file
